MANIFEST.in
README.rst
requirements-tests.txt
requirements.txt
setup.py
creh_pages.egg-info/PKG-INFO
creh_pages.egg-info/SOURCES.txt
creh_pages.egg-info/dependency_links.txt
creh_pages.egg-info/requires.txt
creh_pages.egg-info/top_level.txt
pages/__init__.py
pages/admin.py
pages/managers.py
pages/middleware.py
pages/schema.py
pages/api/__init__.py
pages/api/page/__init__.py
pages/api/page/schema/__init__.py
pages/api/page/schema/nodes/__init__.py
pages/api/page/schema/nodes/page.py
pages/api/page/schema/queries/__init__.py
pages/api/page/schema/queries/page.py
pages/api/slider/__init__.py
pages/api/slider/schema/__init__.py
pages/api/slider/schema/nodes/__init__.py
pages/api/slider/schema/nodes/slider.py
pages/api/slider/schema/queries/__init__.py
pages/api/slider/schema/queries/slider.py
pages/management/__init__.py
pages/management/commands/__init__.py
pages/migrations/0001_initial.py
pages/migrations/0002_insert_default_data.py
pages/migrations/0003_auto_20170607_0959.py
pages/migrations/0004_product.py
pages/migrations/0005_auto_20170608_1255.py
pages/migrations/0006_seotag.py
pages/migrations/0007_auto_20170615_1504.py
pages/migrations/0008_auto_20170616_0136.py
pages/migrations/0009_auto_20170616_0141.py
pages/migrations/0010_page_timer_id.py
pages/migrations/0011_auto_20170616_0214.py
pages/migrations/0012_auto_20170616_0232.py
pages/migrations/__init__.py
pages/models/__init__.py
pages/models/page.py
pages/models/product.py
pages/models/slider.py
pages/tests/__init__.py
pages/tests/test_page.py
pages/tests/test_slider.py
pages/utils/__init__.py
pages/utils/admin.py
pages/utils/constants.py
pages/utils/database.py
pages/utils/image.py